clinterface/__init__.py
clinterface/charDef.py
clinterface/colors.py
clinterface/completion.py
clinterface/cursor.py
clinterface/keyhandler.py
clinterface/printing.py
clinterface/selection.py
clinterface/utils.py
clinterface-0.3.2.dist-info/LICENSE
clinterface-0.3.2.dist-info/METADATA
clinterface-0.3.2.dist-info/WHEEL
clinterface-0.3.2.dist-info/top_level.txt
clinterface-0.3.2.dist-info/RECORD
