Metadata-Version: 2.1
Name: clinterface
Version: 0.3.2
Summary: Simple command line interface library
Home-page: https://github.com/josemvas/clinterface
License: LGPLv3+
Keywords: console cli prompt
Platform: UNKNOWN
Classifier: Programming Language :: Python :: 3 :: Only
Classifier: License :: OSI Approved :: GNU Lesser General Public License v3 or later (LGPLv3+)
Classifier: Operating System :: POSIX
Requires-Python: >=3.6
